automation.py
scripts/smart_files.py
smart_files-0.3.1.dist-info/entry_points.txt
smart_files-0.3.1.dist-info/WHEEL
smart_files-0.3.1.dist-info/METADATA
smart_files-0.3.1.dist-info/RECORD
