Metadata-Version: 2.1
Name: smart-files
Version: 0.3.1
Summary: Automatically sort files by type in your downloads folder
Home-page: https://github.com/ashcaz/smart-files/tree/main
License: MIT
Keywords: automation,downloads,move,automatic,files
Author: BEN
Author-email: benjamin.hill28@gmail.com
Requires-Python: >=3.9,<4.0
Classifier: License :: OSI Approved :: MIT License
Classifier: Programming Language :: Python :: 3
Requires-Dist: click (>=7.1.2,<8.0.0)
Requires-Dist: coverage (>=5.4,<6.0)
Requires-Dist: pytest (>=6.2.2,<7.0.0)
Requires-Dist: pytest-watch (>=4.2.0,<5.0.0)
Requires-Dist: python-crontab (>=2.5.1,<3.0.0)
Project-URL: Repository, https://github.com/ashcaz/smart-files/tree/main
